Metadata-Version: 1.2
Name: apikey
Version: 0.2.4
Summary: save and load API keys from a file
Home-page: http://github.com/ulf1/apikey
Author: Ulf Hamster
Author-email: 554c46@gmail.com
License: Apache License 2.0
Platform: UNKNOWN
Requires-Python: >=3.6
